{
    "2025-07-08": {
        "tableA": {},
        "tableB": {
            "4": [],
            "605": [],
            "1201": [],
            "1804": [],
            "2404": [],
            "3004": [],
            "3603": [],
            "4200": [
                "coasters"
            ],
            "4805": [
                "coasters"
            ],
            "5403": [
                "coasters"
            ],
            "6000": [
                "coasters"
            ],
            "6603": [
                "coasters"
            ],
            "7201": [
                "coasters"
            ],
            "7801": [
                "coasters"
            ],
            "8404": [
                "coasters"
            ],
            "9002": [
                "coasters"
            ],
            "9600": [
                "coasters"
            ],
            "10203": [
                "coasters"
            ]
        },
        "tableC": {
            "5": [],
            "604": [],
            "1203": [],
            "1804": [
                "cup",
                "keychain",
                "paintbrush",
                "palette"
            ],
            "2401": [
                "cup",
                "keychain",
                "paintbrush",
                "palette"
            ],
            "3001": [
                "coasters",
                "cup",
                "keychain",
                "paint",
                "paintbrush",
                "palette"
            ],
            "3601": [
                "coasters",
                "cup",
                "glue",
                "keychain",
                "paint",
                "paintbrush",
                "palette",
                "tissuebox"
            ],
            "4201": [
                "coasters",
                "cup",
                "etchpen",
                "keychain",
                "paint",
                "paintbrush",
                "palette",
                "tissuebox"
            ],
            "4803": [
                "coasters",
                "cup",
                "etchpen",
                "keychain",
                "paint",
                "paintbrush",
                "palette",
                "tissuebox"
            ],
            "5405": [
                "coasters",
                "cup",
                "etchpen",
                "glue",
                "keychain",
                "paint",
                "paintbrush",
                "palette",
                "tissuebox"
            ],
            "6004": [
                "coasters",
                "cup",
                "etchpen",
                "glue",
                "keychain",
                "paint",
                "paintbrush",
                "palette",
                "tissuebox"
            ],
            "6603": [
                "coasters",
                "cup",
                "etchpen",
                "paintbrush",
                "palette",
                "tissuebox"
            ],
            "7205": [
                "coasters",
                "keychain",
                "tissuebox"
            ],
            "7802": [],
            "8403": [],
            "9002": [],
            "9605": [],
            "10205": []
        },
        "tableD": {},
        "tableE": {}
    },
    "2025-07-23": {
        "tableA": {
            "1": [
                "flower",
                "gemset",
                "googlyeyes",
                "keychain",
                "moss",
                "mossframe",
                "stones",
                "varnish"
            ],
            "604": [
                "flower",
                "gemset",
                "googlyeyes",
                "keychain",
                "moss",
                "mossframe",
                "stones",
                "varnish"
            ],
            "1200": [
                "flower",
                "gemset",
                "googlyeyes",
                "keychain",
                "moss",
                "mossframe",
                "stones",
                "varnish"
            ],
            "1800": [
                "coasters",
                "etchpen",
                "gemset",
                "googlyeyes",
                "keychain",
                "moss",
                "mossframe",
                "stones",
                "varnish"
            ],
            "2403": [
                "coasters",
                "gemset",
                "googlyeyes",
                "keychain",
                "moss",
                "mossframe",
                "stones",
                "varnish"
            ],
            "3000": [
                "coasters",
                "keychain",
                "moss",
                "mossframe",
                "paint",
                "paintbrush",
                "palette",
                "plantpot",
                "stones",
                "suncatcher",
                "varnish"
            ],
            "3604": [
                "coasters",
                "keychain",
                "moss",
                "mossframe",
                "plantpot",
                "stones",
                "suncatcher",
                "varnish"
            ],
            "4202": [
                "coasters",
                "keychain",
                "moss",
                "mossframe",
                "plantpot",
                "stones",
                "suncatcher"
            ],
            "4803": [
                "coasters",
                "keychain",
                "mossframe",
                "paint",
                "palette",
                "plantpot",
                "stones",
                "suncatcher"
            ],
            "5405": [
                "coasters",
                "keychain",
                "mossframe",
                "paint",
                "palette",
                "plantpot",
                "stones",
                "suncatcher"
            ],
            "6001": [],
            "6603": [],
            "7205": [],
            "7802": [],
            "8405": [],
            "9004": [],
            "9603": [],
            "10203": []
        },
        "tableB": {
            "4": [],
            "603": [],
            "1203": [],
            "1800": [],
            "2405": [],
            "3003": [],
            "3605": [
                "coasters",
                "cup",
                "paint",
                "paintbrush",
                "palette"
            ],
            "4205": [
                "coasters",
                "cup",
                "paint",
                "paintbrush",
                "palette"
            ],
            "4801": [
                "coasters",
                "cup",
                "paintbrush",
                "palette",
                "varnish"
            ],
            "5400": [
                "coasters"
            ],
            "6004": [
                "coasters",
                "cup",
                "flower",
                "foamball",
                "moss",
                "paint",
                "paintbrush",
                "palette",
                "plantpot",
                "stones"
            ],
            "6601": [
                "coasters",
                "cup",
                "flower",
                "foamball",
                "moss",
                "paintbrush",
                "palette",
                "plantpot",
                "stones"
            ],
            "7201": [
                "coasters",
                "cup",
                "flower",
                "foamball",
                "moss",
                "palette",
                "plantpot",
                "stones"
            ],
            "7802": [
                "coasters",
                "cup",
                "flower",
                "foamball",
                "moss",
                "plantpot",
                "stones"
            ],
            "8402": [
                "coasters",
                "cup",
                "flower",
                "foamball",
                "moss",
                "plantpot",
                "stones"
            ],
            "9005": [
                "flower",
                "foamball",
                "moss",
                "plantpot",
                "stones"
            ],
            "9604": [],
            "10200": []
        },
        "tableC": {},
        "tableD": {
            "2": [],
            "603": [],
            "1203": [],
            "1804": [],
            "2401": [],
            "3000": [
                "coasters",
                "etchpen"
            ],
            "3601": [
                "coasters",
                "etchpen",
                "paintbrush"
            ],
            "4203": [
                "coasters",
                "etchpen",
                "paintbrush"
            ],
            "4805": [
                "coasters",
                "etchpen"
            ],
            "5403": [
                "coasters",
                "etchpen"
            ],
            "6003": [
                "coasters",
                "etchpen"
            ],
            "6603": [],
            "7204": [
                "coasters",
                "cup",
                "paintbrush",
                "palette"
            ],
            "7803": [
                "coasters",
                "cup",
                "flower",
                "paint",
                "paintbrush",
                "palette",
                "photoframe",
                "plantpot"
            ],
            "8400": [
                "coasters",
                "cup",
                "flower",
                "paint",
                "paintbrush",
                "palette",
                "photoframe",
                "plantpot"
            ],
            "9002": [
                "coasters",
                "cup",
                "flower",
                "paint",
                "paintbrush",
                "palette",
                "photoframe",
                "plantpot"
            ],
            "9602": [
                "coasters",
                "cup",
                "paint",
                "paintbrush",
                "palette",
                "photoframe",
                "plantpot"
            ],
            "10203": [
                "coasters",
                "photoframe",
                "plantpot"
            ]
        },
        "tableE": {}
    },
    "2025-07-18": {
        "tableA": {
            "0": [],
            "600": [],
            "1200": [],
            "1805": [],
            "2405": [],
            "3003": [],
            "3605": [],
            "4202": [],
            "4804": [],
            "5405": [
                "coasters"
            ],
            "6004": [
                "coasters",
                "cup",
                "paint",
                "palette",
                "suncatcher"
            ],
            "6602": [
                "coasters",
                "cup",
                "paint",
                "palette",
                "suncatcher"
            ],
            "7202": [
                "coasters",
                "paint",
                "suncatcher"
            ],
            "7800": [
                "coasters",
                "cup",
                "paint",
                "palette",
                "suncatcher"
            ],
            "8405": [
                "coasters",
                "cup",
                "paint",
                "palette",
                "suncatcher",
                "tissuebox"
            ],
            "9004": [
                "coasters",
                "cup",
                "paint",
                "palette",
                "suncatcher",
                "tissuebox"
            ],
            "9603": [
                "coasters",
                "cup",
                "paint",
                "palette",
                "stones",
                "suncatcher",
                "tissuebox"
            ],
            "10202": [
                "coasters",
                "cup",
                "flower",
                "stones",
                "suncatcher",
                "tissuebox"
            ]
        },
        "tableB": {
            "0": [],
            "604": [],
            "1200": [],
            "1800": [],
            "2401": [],
            "3000": [],
            "3604": [],
            "4200": [],
            "4802": [],
            "5400": [],
            "6004": [],
            "6603": [],
            "7202": [],
            "7801": [
                "keychain",
                "paint",
                "paintbrush",
                "palette",
                "photoframe"
            ],
            "8405": [
                "keychain",
                "paint",
                "paintbrush",
                "palette",
                "photoframe"
            ],
            "9002": [
                "keychain",
                "paint",
                "paintbrush",
                "palette",
                "photoframe"
            ],
            "9601": [
                "keychain",
                "paint",
                "paintbrush",
                "palette",
                "photoframe",
                "tissuebox"
            ],
            "10201": [
                "flower",
                "keychain",
                "paintbrush",
                "palette",
                "photoframe",
                "tissuebox"
            ]
        },
        "tableC": {
            "1": [],
            "601": [],
            "1204": [],
            "1805": [
                "coasters",
                "etchpen"
            ],
            "2400": [
                "coasters",
                "etchpen",
                "paint",
                "paintbrush",
                "palette",
                "plantpot"
            ],
            "3005": [
                "etchpen",
                "mossframe",
                "paintbrush"
            ],
            "3601": [
                "etchpen",
                "flower",
                "moss",
                "mossframe",
                "paintbrush",
                "stones"
            ],
            "4203": [
                "etchpen",
                "flower",
                "moss",
                "mossframe",
                "paintbrush",
                "stones"
            ],
            "4805": [
                "etchpen",
                "flower",
                "moss",
                "mossframe",
                "paintbrush",
                "stones"
            ],
            "5404": [
                "etchpen",
                "flower",
                "gemset",
                "moss",
                "mossframe",
                "paintbrush",
                "stones"
            ],
            "6004": [
                "etchpen",
                "flower",
                "gemset",
                "mossframe",
                "paintbrush",
                "stones"
            ],
            "6602": [
                "etchpen",
                "flower",
                "moss",
                "mossframe",
                "paintbrush",
                "stones"
            ],
            "7200": [
                "etchpen",
                "flower",
                "moss",
                "mossframe",
                "paintbrush",
                "palette",
                "stones"
            ],
            "7802": [
                "flower",
                "moss",
                "mossframe",
                "paintbrush",
                "palette",
                "stones",
                "tissuebox"
            ],
            "8402": [
                "flower",
                "moss",
                "mossframe",
                "paintbrush",
                "palette",
                "stones",
                "tissuebox"
            ],
            "9004": [
                "flower",
                "moss",
                "mossframe",
                "paintbrush",
                "palette",
                "photoframe",
                "stones",
                "tissuebox"
            ],
            "9600": [
                "flower",
                "moss",
                "mossframe",
                "paintbrush",
                "palette",
                "photoframe",
                "stones",
                "tissuebox",
                "varnish"
            ],
            "10205": [
                "flower",
                "moss",
                "mossframe",
                "paintbrush",
                "palette",
                "photoframe",
                "stones",
                "tissuebox"
            ]
        },
        "tableD": {
            "0": [],
            "600": [],
            "1205": [],
            "1802": [],
            "2400": [],
            "3003": [
                "etchpen",
                "googlyeyes",
                "keychain",
                "moss",
                "plantpot"
            ],
            "3604": [
                "etchpen",
                "flower",
                "moss"
            ],
            "4205": [
                "etchpen",
                "mossframe"
            ],
            "4800": [
                "etchpen",
                "keychain"
            ],
            "5405": [
                "etchpen",
                "keychain"
            ],
            "6003": [
                "etchpen",
                "keychain"
            ],
            "6601": [
                "etchpen",
                "keychain"
            ],
            "7204": [
                "etchpen",
                "keychain"
            ],
            "7800": [
                "etchpen",
                "keychain"
            ],
            "8403": [
                "etchpen",
                "keychain"
            ],
            "9000": [
                "etchpen",
                "keychain"
            ],
            "9600": [
                "etchpen",
                "flower",
                "gemset",
                "keychain",
                "stones"
            ],
            "10202": [
                "etchpen",
                "flower",
                "gemset",
                "keychain",
                "stones"
            ]
        },
        "tableE": {
            "0": [],
            "604": [],
            "1201": [],
            "1801": [],
            "2405": [],
            "3004": [],
            "3605": [],
            "4202": [],
            "4803": [
                "cup",
                "paint",
                "paintbrush",
                "palette",
                "photoframe",
                "plantpot",
                "varnish"
            ],
            "5401": [
                "cup",
                "keychain",
                "paint",
                "paintbrush",
                "palette",
                "photoframe",
                "plantpot",
                "varnish"
            ],
            "6001": [
                "cup",
                "keychain",
                "paint",
                "paintbrush",
                "palette",
                "photoframe",
                "plantpot",
                "varnish"
            ],
            "6601": [
                "cup",
                "keychain",
                "paint",
                "paintbrush",
                "palette",
                "photoframe",
                "plantpot",
                "varnish"
            ],
            "7205": [
                "cup",
                "keychain",
                "paint",
                "paintbrush",
                "palette",
                "photoframe",
                "plantpot",
                "varnish"
            ],
            "7804": [
                "cup",
                "keychain",
                "paint",
                "paintbrush",
                "palette",
                "photoframe",
                "plantpot",
                "varnish"
            ],
            "8400": [
                "cup",
                "etchpen",
                "keychain",
                "paint",
                "paintbrush",
                "palette",
                "photoframe",
                "plantpot",
                "varnish"
            ],
            "9003": [
                "cup",
                "etchpen",
                "keychain",
                "paint",
                "paintbrush",
                "palette",
                "photoframe",
                "plantpot",
                "varnish"
            ],
            "9601": [
                "cup",
                "etchpen",
                "keychain",
                "paint",
                "paintbrush",
                "palette",
                "photoframe",
                "plantpot",
                "varnish"
            ],
            "10202": [
                "cup",
                "etchpen",
                "keychain",
                "paint",
                "paintbrush",
                "palette",
                "photoframe",
                "plantpot",
                "varnish"
            ]
        }
    },
    "2025-07-09": {
        "tableA": {},
        "tableB": {},
        "tableC": {
            "3": [],
            "604": [],
            "1204": [],
            "1803": [],
            "2402": [],
            "3002": [],
            "3603": [],
            "4201": [],
            "4803": [],
            "5402": [],
            "6001": [],
            "6603": [],
            "7200": [
                "coasters",
                "cup",
                "etchpen",
                "gemset",
                "glue",
                "paint",
                "paintbrush",
                "palette",
                "photoframe",
                "stones",
                "tissuebox"
            ],
            "7804": [
                "cup",
                "etchpen",
                "gemset",
                "glue",
                "paint",
                "paintbrush",
                "palette",
                "photoframe",
                "stones",
                "tissuebox"
            ],
            "8402": [
                "coasters",
                "cup",
                "etchpen",
                "paint",
                "paintbrush",
                "palette",
                "photoframe",
                "stones",
                "tissuebox"
            ],
            "9003": [
                "coasters",
                "cup",
                "etchpen",
                "gemset",
                "paint",
                "paintbrush",
                "palette",
                "photoframe",
                "stones",
                "tissuebox"
            ],
            "9601": [
                "coasters",
                "cup",
                "etchpen",
                "gemset",
                "glue",
                "paint",
                "paintbrush",
                "palette",
                "photoframe",
                "stones",
                "tissuebox"
            ],
            "10202": [
                "coasters",
                "cup",
                "etchpen",
                "gemset",
                "paint",
                "paintbrush",
                "palette",
                "photoframe",
                "stones",
                "tissuebox"
            ]
        },
        "tableD": {
            "2": [],
            "600": [
                "coasters",
                "cup",
                "etchpen",
                "gemset",
                "glue",
                "stones"
            ],
            "1203": [
                "coasters",
                "cup",
                "etchpen",
                "gemset",
                "glue",
                "stones"
            ],
            "1804": [
                "coasters",
                "cup",
                "etchpen",
                "gemset",
                "glue",
                "stones"
            ],
            "2400": [
                "cup",
                "etchpen",
                "gemset",
                "glue",
                "stones"
            ],
            "3004": [
                "cup",
                "etchpen",
                "gemset",
                "glue",
                "stones"
            ],
            "3601": [
                "mossframe"
            ],
            "4204": [
                "etchpen",
                "mossframe"
            ],
            "4804": [
                "etchpen",
                "mossframe",
                "paint",
                "paintbrush",
                "palette"
            ],
            "5403": [
                "cup",
                "etchpen",
                "mossframe",
                "paint",
                "paintbrush",
                "palette"
            ],
            "6001": [
                "cup",
                "etchpen",
                "mossframe",
                "paint",
                "paintbrush",
                "palette"
            ],
            "6604": [
                "cup",
                "etchpen",
                "mossframe",
                "paint",
                "paintbrush",
                "palette"
            ],
            "7203": [
                "cup",
                "glue",
                "mossframe",
                "palette",
                "stones"
            ],
            "7805": [
                "cup",
                "glue",
                "moss",
                "mossframe",
                "palette"
            ],
            "8400": [
                "cup",
                "mossframe",
                "palette",
                "varnish"
            ],
            "9004": [
                "mossframe"
            ],
            "9604": [
                "mossframe"
            ],
            "10203": []
        },
        "tableE": {}
    },
    "2025-07-16": {
        "tableA": {},
        "tableB": {
            "1": [],
            "601": [],
            "1205": [],
            "1800": [],
            "2403": [],
            "3005": [],
            "3602": [
                "etchpen",
                "keychain"
            ],
            "4202": [
                "etchpen",
                "keychain"
            ],
            "4800": [
                "etchpen",
                "keychain"
            ],
            "5401": [
                "etchpen",
                "keychain"
            ],
            "6005": [
                "etchpen",
                "keychain"
            ],
            "6605": [
                "coasters",
                "etchpen",
                "keychain"
            ],
            "7202": [
                "coasters",
                "etchpen",
                "keychain"
            ],
            "7801": [
                "coasters",
                "etchpen"
            ],
            "8400": [
                "coasters",
                "etchpen"
            ],
            "9004": [
                "coasters",
                "etchpen"
            ],
            "9605": [
                "coasters",
                "etchpen"
            ],
            "10200": [
                "coasters",
                "etchpen"
            ]
        },
        "tableC": {},
        "tableD": {},
        "tableE": {}
    }
}